open_sparkdq-0.1.10.dist-info/licenses/LICENSE
sparkdq/__init__.py
sparkdq/cli/main.py
sparkdq/config/env.py
sparkdq/config/loader.py
sparkdq/config/schema.py
sparkdq/core/__init__.py
sparkdq/core/models.py
sparkdq/core/registry.py
sparkdq/core/reporter.py
sparkdq/core/runner.py
sparkdq/core/spark.py
sparkdq/core/validators/__init__.py
sparkdq/core/validators/base.py
sparkdq/core/validators/chispa_unit.py
sparkdq/core/validators/dataframe.py
sparkdq/core/validators/expression.py
sparkdq/core/validators/function_validators.py
sparkdq/core/validators/not_null.py
sparkdq/core/validators/pydeequ_validators.py
sparkdq/core/validators/range.py
sparkdq/core/validators/regex.py
sparkdq/core/validators/uniqueness.py
sparkdq/examples/batch_example.py
sparkdq/examples/streaming_example.py
sparkdq/integrations/streaming.py
sparkdq/observability/otel.py
sparkdq/profiling/profiler.py
sparkdq/resources/open_spark_dlh_dq.yml
sparkdq/resources/deequ/deequ-2.0.12-spark-3.3.jar
sparkdq/tests/test_chispa_integration.py
sparkdq/tests/test_cli.py
sparkdq/tests/test_pydeequ_integration.py
sparkdq/tests/test_runner.py
sparkdq/tests/test_validator_contracts.py
sparkdq/tests/test_validators.py
sparkdq/tests/test_yaml_loader.py
sparkdq/user_checks/example_checks.py
open_sparkdq-0.1.10.dist-info/METADATA
open_sparkdq-0.1.10.dist-info/WHEEL
open_sparkdq-0.1.10.dist-info/entry_points.txt
open_sparkdq-0.1.10.dist-info/top_level.txt
open_sparkdq-0.1.10.dist-info/RECORD
