Metadata-Version: 2.4
Name: open-sparkdq
Version: 0.1.10
Summary: Plug-and-play Data Quality + Unit Testing for PySpark (batch & streaming) with YAML config, profiling, and optional OpenTelemetry hooks.
Author-email: Aashish Kumar <aashish72.it@gmail.com>
License: MIT License
Project-URL: Homepage, https://github.com/aashish72it/open-spark-dlh-dq
Project-URL: Issues, https://github.com/aashish72it/open-spark-dlh-dq/issues
Requires-Python: >=3.9
License-File: LICENSE
Requires-Dist: pyspark<3.6,>=3.3
Requires-Dist: pyyaml>=6.0
Requires-Dist: chispa>=0.9.2
Requires-Dist: jsonschema>=4.0
Requires-Dist: pydeequ>=1.2.0
Provides-Extra: otel
Requires-Dist: opentelemetry-sdk>=1.24.0; extra == "otel"
Requires-Dist: opentelemetry-api>=1.24.0; extra == "otel"
Provides-Extra: docs
Requires-Dist: mkdocs; extra == "docs"
Requires-Dist: mkdocs-material; extra == "docs"
Provides-Extra: dev
Requires-Dist: pytest>=7.0; extra == "dev"
Requires-Dist: pytest-cov; extra == "dev"
Requires-Dist: build; extra == "dev"
Requires-Dist: twine; extra == "dev"
Dynamic: license-file
